png_to_pptx/__init__.py
png_to_pptx/converter.py
png_to_pptx-0.1.dist-info/METADATA
png_to_pptx-0.1.dist-info/WHEEL
png_to_pptx-0.1.dist-info/top_level.txt
png_to_pptx-0.1.dist-info/RECORD
