Metadata-Version: 2.1
Name: png_to_pptx
Version: 0.1
Summary: A tool to convert PNG images to a PPTX presentation with a 16:9 aspect ratio.
Home-page: https://github.com/TheProlifical/ppt-to-png_package
Author: Ahson
Author-email: itsahson1978@gmail.com
Classifier: Programming Language :: Python :: 3
Classifier: License :: OSI Approved :: BSD License
Classifier: Operating System :: OS Independent
Requires-Python: >=3.6
Requires-Dist: python-pptx
Requires-Dist: Pillow
